<image>
<filename>image_104139.jpg</filename>
<folder></folder>
<size>
<width>256</width>
<height>256</height>
</size>
<origSize>
<width>800</width>
<height>600</height>
</origSize>
<generated>0</generated>
</image>
<file>
<filename>image_104139.xml</filename>
<folder></folder>
</file>
<object>
<objectId>6</objectId>
<name>personSittingBack</name>
<masks>
<filename>masks/image_104139.mat</filename>
</masks>
<keyword>person</keyword>
</object>
<objImgSrc>
<filename>img_0349.jpg</filename>
<folder>oct6_static_office_bldg200</folder>
<size>
<width>800</width>
<height>600</height>
</size>
<origSize>
<width>1600</width>
<height>1200</height>
</origSize>
</objImgSrc>
<bgImgSrc>
<filename>img_0349.jpg</filename>
<folder>oct6_static_office_bldg200</folder>
<size>
<width>800</width>
<height>600</height>
</size>
<origSize>
<width>1600</width>
<height>1200</height>
</origSize>
</bgImgSrc>
