<image>
<filename>image_003922.jpg</filename>
<folder></folder>
<size>
<width>341</width>
<height>256</height>
</size>
<origSize>
<width>800</width>
<height>600</height>
</origSize>
<generated>1</generated>
</image>
<file>
<filename>image_003922.xml</filename>
<folder></folder>
</file>
<object>
<objectId>1</objectId>
<name>road</name>
<masks>
<filename>masks/image_003922.mat</filename>
</masks>
<keyword>road</keyword>
</object>
<objImgSrc>
<filename>IMG_6955.jpg</filename>
<folder>static_outdoor_road_spain</folder>
<size>
<width>800</width>
<height>600</height>
</size>
<origSize>
<width>2048</width>
<height>1536</height>
</origSize>
</objImgSrc>
<bgImgSrc>
<filename>img_1969.jpg</filename>
<folder>static_village_outdoor_2005</folder>
<size>
<width>800</width>
<height>600</height>
</size>
<origSize>
<width>2592</width>
<height>1944</height>
</origSize>
</bgImgSrc>
