<image>
<filename>image_007931.jpg</filename>
<folder></folder>
<size>
<width>256</width>
<height>256</height>
</size>
<origSize>
<width>800</width>
<height>800</height>
</origSize>
<generated>1</generated>
</image>
<file>
<filename>image_007931.xml</filename>
<folder></folder>
</file>
<object>
<objectId>2</objectId>
<name>sea water</name>
<masks>
<filename>masks/image_007931.mat</filename>
</masks>
<keyword>water</keyword>
</object>
<objImgSrc>
<filename>coast_natu816.jpg</filename>
<folder>spatial_envelope_256x256_static_8outdoorcategories</folder>
<size>
<width>800</width>
<height>800</height>
</size>
<origSize>
<width>256</width>
<height>256</height>
</origSize>
</objImgSrc>
<bgImgSrc>
<filename>coast_cdmc123.jpg</filename>
<folder>spatial_envelope_256x256_static_8outdoorcategories</folder>
<size>
<width>800</width>
<height>800</height>
</size>
<origSize>
<width>256</width>
<height>256</height>
</origSize>
</bgImgSrc>
